py2pygetweatherinfo/__init__.py
py2pygetweatherinfo/getweatherinfo.py
py2pygetweatherinfo/weatherInfo.py
py2pygetweatherinfo-0.0.4.dist-info/LICENSE.txt
py2pygetweatherinfo-0.0.4.dist-info/METADATA
py2pygetweatherinfo-0.0.4.dist-info/WHEEL
py2pygetweatherinfo-0.0.4.dist-info/top_level.txt
py2pygetweatherinfo-0.0.4.dist-info/RECORD
