Metadata-Version: 2.1
Name: py2pygetweatherinfo
Version: 0.0.4
Summary: Finding the Weather Information of a Place
Home-page: https://github.com/kpajay17/
Author: Ajay Prajapati
Author-email: kpajay.17@gmail.com
License: UNKNOWN
Platform: UNKNOWN
Classifier: Programming Language :: Python :: 3
Classifier: License :: OSI Approved :: MIT License
Classifier: Operating System :: OS Independent
